half_json/__init__.py
half_json/core.py
half_json/json_util.py
half_json/main.py
jsonfixer-0.2.0.dist-info/METADATA
jsonfixer-0.2.0.dist-info/WHEEL
jsonfixer-0.2.0.dist-info/entry_points.txt
jsonfixer-0.2.0.dist-info/licenses/LICENSE
jsonfixer-0.2.0.dist-info/RECORD
