Metadata-Version: 2.1
Name: jsonfixer
Version: 0.2.0
Summary: jsonfixer: fix invalid json: broken-json / truncated-json.
Author-Email: alingse <alingse@foxmail.com>
License: MIT
Classifier: License :: OSI Approved :: MIT License
Classifier: Operating System :: OS Independent
Classifier: Programming Language :: Python :: 3
Project-URL: Homepage, https://github.com/half-pie/half-json
Requires-Python: >=3.10
